fyntex/__init__.py
fyntex/drf_pagination_utils/__init__.py
fyntex/drf_pagination_utils/py.typed
fyntex/drf_pagination_utils/styles.py
fyntex/drf_pagination_utils/tests/__init__.py
fyntex/drf_pagination_utils/tests/settings.py
fyntex/drf_pagination_utils/tests/test_styles.py
fyntex_drf_pagination_utils-1.5.3.dist-info/LICENSE
fyntex_drf_pagination_utils-1.5.3.dist-info/METADATA
fyntex_drf_pagination_utils-1.5.3.dist-info/WHEEL
fyntex_drf_pagination_utils-1.5.3.dist-info/top_level.txt
fyntex_drf_pagination_utils-1.5.3.dist-info/RECORD
